geojson_length/__init__.py
geojson_length/exc.py
geojson_length/geojson_length.py
geojson_length-0.4.0.dist-info/LICENSE
geojson_length-0.4.0.dist-info/WHEEL
geojson_length-0.4.0.dist-info/METADATA
geojson_length-0.4.0.dist-info/RECORD
