Metadata-Version: 2.1
Name: geojson-length
Version: 0.4.0
Summary: Calculate the length of a GeoJSON LineString or MultiLineString
License: MIT
Author: Zaitra
Author-email: info@zaitra.io
Requires-Python: >=3.8,<4.0
Classifier: License :: OSI Approved :: MIT License
Classifier: Programming Language :: Python :: 3
Classifier: Programming Language :: Python :: 3.10
Classifier: Programming Language :: Python :: 3.8
Classifier: Programming Language :: Python :: 3.9
Requires-Dist: geopy (==2.2.0)
